{"status": "ok", "totalResults": 21, "articles": [{"source": {"id": "fox-news", "name": "Fox News"}, "author": "Emma Parry", "title": "Justin TImberlake, Jessica Biel spotted for the first time together since his hand-holding incident", "description": "Justin Timberlake and wife Jessica Biel have been pictured together for the first time since the singer was caught holding hands with a co-star.", "url": "https://www.foxnews.com/entertainment/justin-timberlake-jessica-biel-spotted-first-time-hand-holding-incident", "urlToImage": "https://static.foxnews.com/foxnews.com/content/uploads/2019/12/Jessica-Biel-Justin-Timberlake.jpg", "publishedAt": "2020-01-11T00:02:14Z", "content": "Justin\u00a0Timberlake and wife Jessica Biel have been pictured together for the first time since the singer was caught holding hands with a co-star.\r\nThe couple appeared to have put the incident behind them as they were spotted laughing and joking during an intim\u2026 [+4507 chars]"}]}